<?xml version="1.0" encoding="UTF-8"?>
<!DOCTYPE mapper PUBLIC "-//mybatis.org//DTD Mapper 3.0//EN" "http://mybatis.org/dtd/mybatis-3-mapper.dtd">
<mapper namespace="com.guide.ssm.module.user.mapper.TbAdviceMapper">
  <resultMap id="BaseResultMap" type="com.guide.ssm.module.user.pojo.TbAdvice">
    <!--
      WARNING - @mbggenerated
      This element is automatically generated by MyBatis Generator, do not modify.
    -->
    <constructor>
      <idArg column="ADid" javaType="java.lang.String" jdbcType="CHAR" />
      <arg column="Title" javaType="java.lang.String" jdbcType="VARCHAR" />
      <arg column="Advice" javaType="java.lang.String" jdbcType="VARCHAR" />
      <arg column="type" javaType="java.lang.String" jdbcType="CHAR" />
      <arg column="Atime" javaType="java.util.Date" jdbcType="TIMESTAMP" />
      <arg column="Status" javaType="java.lang.String" jdbcType="CHAR" />
      <arg column="Vid" javaType="java.lang.String" jdbcType="CHAR" />
    </constructor>
  </resultMap>
  <delete id="deleteByPrimaryKey" parameterType="java.lang.String">
    <!--
      WARNING - @mbggenerated
      This element is automatically generated by MyBatis Generator, do not modify.
    -->
    delete from tb_advice
    where ADid = #{adid,jdbcType=CHAR}
  </delete>
  <insert id="insert" parameterType="com.guide.ssm.module.user.pojo.TbAdvice">
    <!--
      WARNING - @mbggenerated
      This element is automatically generated by MyBatis Generator, do not modify.
    -->
    insert into tb_advice (ADid, Title, Advice, 
      type, Atime, Status, Vid
      )
    values (#{adid,jdbcType=CHAR}, #{title,jdbcType=VARCHAR}, #{advice,jdbcType=VARCHAR}, 
      #{type,jdbcType=CHAR}, #{atime,jdbcType=TIMESTAMP}, #{status,jdbcType=CHAR}, #{vid,jdbcType=CHAR}
      )
  </insert>
  <update id="updateByPrimaryKey" parameterType="com.guide.ssm.module.user.pojo.TbAdvice">
    <!--
      WARNING - @mbggenerated
      This element is automatically generated by MyBatis Generator, do not modify.
    -->
    update tb_advice
    set Title = #{title,jdbcType=VARCHAR},
      Advice = #{advice,jdbcType=VARCHAR},
      type = #{type,jdbcType=CHAR},
      Atime = #{atime,jdbcType=TIMESTAMP},
      Status = #{status,jdbcType=CHAR},
      Vid = #{vid,jdbcType=CHAR}
    where ADid = #{adid,jdbcType=CHAR}
  </update>
  <select id="selectByPrimaryKey" parameterType="java.lang.String" resultMap="BaseResultMap">
    <!--
      WARNING - @mbggenerated
      This element is automatically generated by MyBatis Generator, do not modify.
    -->
    select ADid, Title, Advice, type, Atime, Status, Vid
    from tb_advice
    where ADid = #{adid,jdbcType=CHAR}
  </select>
  <select id="selectAll" resultMap="BaseResultMap">
    <!--
      WARNING - @mbggenerated
      This element is automatically generated by MyBatis Generator, do not modify.
    -->
    select ADid, Title, Advice, type, Atime, Status, Vid
    from tb_advice
  </select>
</mapper>